{
    "enables": {
        "features": {
            "dad_greeting": true,
            "nato_censor": true
        },
        "channelsDisabled": [
            "691243089704255498",
            "690901771220025394",
            "652499918560297004",
            "690524780377669632"
        ]
    },
    "words": {
        "word": [
            "i",
            "___",
            "is",
            "start",
            "msg",
            "man",
            "what",
            "discord",
            "so",
            "are",
            "using",
            "z",
            "tictactoe",
            "this",
            "thing",
            "wtf",
            "the",
            "on",
            "hello",
            "ok",
            "no",
            "am",
            "good",
            "you",
            "data",
            "fixed",
            "for",
            "to",
            "store",
            "json",
            "array",
            "there",
            "called",
            "collection",
            "w",
            "t",
            "f",
            "problem",
            "lol",
            "oh",
            "damn",
            "seems",
            "useful",
            "whattt",
            "dun",
            "wanna",
            "user",
            "embed",
            "it",
            "neat",
            "but",
            "complex",
            "functions",
            "can",
            "be",
            "directly",
            "used",
            "arrays",
            "which",
            "listed",
            "doc",
            "foreachv",
            "nvm",
            "_________",
            "annoying",
            "looks",
            "like",
            "embeds",
            "only",
            "options",
            "left",
            "or",
            "not",
            "hkjfhe",
            "sdfslkjfdlksdjlfksjlkfj",
            "sksfjk",
            "show",
            "10",
            "script",
            "v",
            "rr",
            "h",
            "a",
            "resctrictions",
            "restrictions",
            "function",
            "embedfrom",
            "author",
            "title",
            "const",
            "new",
            "messageembed",
            "setcolor",
            "0099ff",
            "settitle",
            "setauthor",
            "setdescription",
            "return",
            "most",
            "logout"
        ],
        "count": [
            6,
            6,
            5,
            5,
            8,
            15,
            3,
            4,
            2,
            2,
            2,
            2,
            2,
            2,
            2,
            2,
            2,
            2,
            1,
            1,
            3,
            1,
            1,
            1,
            2,
            1,
            1,
            1,
            1,
            1,
            1,
            1,
            1,
            1,
            1,
            1,
            1,
            1,
            2,
            1,
            1,
            1,
            2,
            1,
            1,
            1,
            1,
            3,
            1,
            1,
            1,
            1,
            1,
            1,
            1,
            1,
            1,
            1,
            1,
            1,
            1,
            1,
            1,
            1,
            1,
            1,
            1,
            1,
            1,
            1,
            1,
            1,
            1,
            1,
            1,
            1,
            1,
            1,
            2,
            7,
            6,
            5,
            3,
            1,
            1,
            2,
            1,
            2,
            2,
            1,
            1,
            1,
            1,
            1,
            1,
            1,
            1,
            1,
            1,
            3
        ]
    }
}